ddump/__init__.py
ddump/_version.py
ddump/common.py
ddump/merge.py
ddump/api/README.md
ddump/api/__init__.py
ddump/api/columns.py
ddump/api/common.py
ddump/api/dump.py
ddump/api/merge.py
ddump/db/README.md
ddump/db/__init__.py
ddump/db/common.py
ddump/db/dump.py
ddump/db/merge.py
ddump/db/tool.py
ddump-0.3.2.dist-info/METADATA
ddump-0.3.2.dist-info/WHEEL
ddump-0.3.2.dist-info/licenses/LICENSE
ddump-0.3.2.dist-info/RECORD
