Metadata-Version: 2.4
Name: ddump
Version: 0.3.2
Summary: A data dump tool
Author-email: wukan <wu-kan@163.com>
License: MIT License
License-File: LICENSE
Classifier: Development Status :: 4 - Beta
Classifier: Programming Language :: Python
Requires-Python: >=3.6
Requires-Dist: ksrpc>=0.6.0
Requires-Dist: loguru
Requires-Dist: more-itertools
Requires-Dist: pandas
Requires-Dist: pyarrow
Requires-Dist: pymysql
Requires-Dist: sqlalchemy>=1.4
Requires-Dist: tenacity
